reprozip_jupyter/__init__.py
reprozip_jupyter/main.py
reprozip_jupyter/notebook-extension.js
reprozip_jupyter/run.py
reprozip_jupyter/server_extension.py
reprozip_jupyter/trace.py
reprozip_jupyter-1.2.dist-info/LICENSE.txt
reprozip_jupyter-1.2.dist-info/METADATA
reprozip_jupyter-1.2.dist-info/WHEEL
reprozip_jupyter-1.2.dist-info/entry_points.txt
reprozip_jupyter-1.2.dist-info/top_level.txt
reprozip_jupyter-1.2.dist-info/RECORD
