Metadata-Version: 2.1
Name: reprozip-jupyter
Version: 1.2
Summary: Jupyter Notebook tracing/reproduction using ReproZip
Home-page: https://www.reprozip.org/
Author: Remi Rampin, Fernando Chirigati, Dennis Shasha, Juliana Freire
Author-email: reprozip@nyu.edu
Maintainer: Remi Rampin
Maintainer-email: remi@rampin.org
License: BSD
Project-URL: Documentation, https://docs.reprozip.org/
Project-URL: Examples, https://examples.reprozip.org/
Project-URL: Source, https://github.com/VIDA-NYU/reprozip
Project-URL: Bug Tracker, https://github.com/VIDA-NYU/reprozip/issues
Project-URL: Chat, https://riot.im/app/#/room/#reprozip:matrix.org
Project-URL: Changelog, https://github.com/VIDA-NYU/reprozip/blob/1.x/CHANGELOG.md
Keywords: reprozip,reprounzip,reproducibility,provenance,vida,nyu,jupyter,notebook
Classifier: Development Status :: 4 - Beta
Classifier: Intended Audience :: Science/Research
Classifier: License :: OSI Approved :: BSD License
Classifier: Programming Language :: Python :: 2.7
Classifier: Programming Language :: Python :: 3
Classifier: Topic :: Scientific/Engineering
Classifier: Topic :: System :: Archiving
License-File: LICENSE.txt
Requires-Dist: rpaths
Requires-Dist: notebook
Requires-Dist: jupyter-client
Requires-Dist: nbformat
Requires-Dist: nbconvert
Requires-Dist: reprounzip (>=1.0)
